setup.py
examples/docs_app.py
examples/example_app_simple.py
examples/example_app_with_option_menu.py
examples/example_data_editor.py
streamlit_permalink/__init__.py
streamlit_permalink/constants.py
streamlit_permalink/exceptions.py
streamlit_permalink/url_validators.py
streamlit_permalink/utils.py
streamlit_permalink/widgets.py
streamlit_permalink/handlers/__init__.py
streamlit_permalink/handlers/checkbox.py
streamlit_permalink/handlers/color_picker.py
streamlit_permalink/handlers/data_editor.py
streamlit_permalink/handlers/date_input.py
streamlit_permalink/handlers/handler.py
streamlit_permalink/handlers/multiselect.py
streamlit_permalink/handlers/number_input.py
streamlit_permalink/handlers/option_menu.py
streamlit_permalink/handlers/pills.py
streamlit_permalink/handlers/radio.py
streamlit_permalink/handlers/segmented_control.py
streamlit_permalink/handlers/select_slider.py
streamlit_permalink/handlers/selectbox.py
streamlit_permalink/handlers/slider.py
streamlit_permalink/handlers/text_area.py
streamlit_permalink/handlers/text_input.py
streamlit_permalink/handlers/time_input.py
streamlit_permalink/handlers/toggle.py
streamlit_permalink_pg-1.5.0.dist-info/licenses/LICENSE
tests/__init__.py
tests/test_checkbox.py
tests/test_color_picker.py
tests/test_compression.py
tests/test_custom_compression.py
tests/test_date_input.py
tests/test_multiselect.py
tests/test_non_stateful.py
tests/test_number_input.py
tests/test_on_change.py
tests/test_radio.py
tests/test_select_slider.py
tests/test_selectbox.py
tests/test_slider.py
tests/test_stateful.py
tests/test_text_area.py
tests/test_text_input.py
tests/test_time_input.py
tests/test_toggle.py
tests/test_utils_url.py
tests/utils.py
streamlit_permalink_pg-1.5.0.dist-info/METADATA
streamlit_permalink_pg-1.5.0.dist-info/WHEEL
streamlit_permalink_pg-1.5.0.dist-info/top_level.txt
streamlit_permalink_pg-1.5.0.dist-info/RECORD
