Metadata-Version: 2.4
Name: streamlit-permalink-pg
Version: 1.5.0
Summary: Effortless permalinks in Streamlit apps. Synchronize Streamlit Widgets with URL Query Params.
Author-email: Patrick Garrett <pgarrett@scripps.edu>, Franciszek Piszcz <franciszek.piszcz@rtbhouse.com>
Project-URL: repository, https://github.com/pgarrett-scripps/streamlit-permalink
Requires-Python: >=3.9
License-File: LICENSE
Requires-Dist: streamlit>=1.4.0
Requires-Dist: packaging>=15.0
Provides-Extra: test
Requires-Dist: pytest>=8.0.0; extra == "test"
Requires-Dist: pytest-cov>=4.1.0; extra == "test"
Requires-Dist: pytest-xdist>=3.5.0; extra == "test"
Dynamic: license-file
